{"cameraMode":{"drawMode":0,"name":"Shaded","section":"Shading Mode"},"sceneLighting":true,"audioPlay":false,"sceneViewState":{"m_AlwaysRefresh":false,"showFog":true,"showSkybox":true,"showFlares":true,"showImageEffects":true,"showParticleSystems":true,"showVisualEffectGraphs":true,"m_FxEnabled":true},"in2DMode":false,"pivot":{"x":-67.31543731689453,"y":-93.8251953125,"z":-86.2047119140625},"rotation":{"x":-0.14795148372650147,"y":0.8511382937431336,"z":-0.35691386461257937,"w":-0.3558322787284851},"size":71.7611083984375,"orthographic":false}